biopy/__init__.py
biopy/datasets/ImageDataset.py
biopy/datasets/__init__.py
biopy/datasets/datasets_gdc.py
biopy/datasets/datasets_nature.py
biopy/datasets/datasets_nature_a549.py
biopy/experiments/__init__.py
biopy/experiments/grid_baseline.py
biopy/metrics/__init__.py
biopy/metrics/latent_metrics.py
biopy/metrics/reconstruction_error.py
biopy/metrics/roc_cnn_rf.py
biopy/metrics/roc_random_forest.py
biopy/models/Baseline.py
biopy/models/ExprAutoEncoders.py
biopy/models/ImageAAEresnet.py
biopy/models/ImageAutoEncoders.py
biopy/models/JointLatentGenerator.py
biopy/models/Translators.py
biopy/models/__init__.py
biopy/statistic/__init__.py
biopy/statistic/distributions.py
biopy/statistic/sampling.py
biopy/training/__init__.py
biopy/training/aae_trainer.py
biopy/training/baseline_trainer.py
biopy/training/distribution_trainer.py
biopy/training/joint_double_discr.py
biopy/training/joint_trainer.py
biopy/training/saae_trainer.py
biopy/training/trainer.py
biopy/training/trainer_wrapper.py
biopy/training/vae_trainer.py
biopy/utils/__init__.py
biopy/utils/download_dataset_gdc.py
biopy/utils/download_dataset_nature.py
biopy/utils/hparams.py
biopy/utils/plots.py
biopy/utils/threads.py
biopy/utils/utils.py
biopy-0.1.2.dist-info/LICENSE
biopy-0.1.2.dist-info/METADATA
biopy-0.1.2.dist-info/WHEEL
biopy-0.1.2.dist-info/top_level.txt
biopy-0.1.2.dist-info/RECORD
