Metadata-Version: 2.1
Name: biopy
Version: 0.1.2
Summary: DomainTranslation toolkit
Home-page: https://github.com/BioPyTeam/biopy
Author: BioPyTeam
Author-email: gabriele.trivigno@studenti.polito.it
License: UNKNOWN
Project-URL: Documentation, https://biopy-proj.readthedocs.io/en/latest/index.html
Platform: UNKNOWN
Classifier: Programming Language :: Python :: 3
Classifier: License :: OSI Approved :: MIT License
Classifier: Operating System :: OS Independent
Requires-Python: >=3.7
License-File: LICENSE
